mp_api/client/__init__.py
mp_api/client/mprester.py
mp_api/client/core/__init__.py
mp_api/client/core/_oxygen_evolution.py
mp_api/client/core/client.py
mp_api/client/core/settings.py
mp_api/client/core/utils.py
mp_api/client/routes/__init__.py
mp_api/client/routes/_general_store.py
mp_api/client/routes/_messages.py
mp_api/client/routes/_user_settings.py
mp_api/client/routes/materials/__init__.py
mp_api/client/routes/materials/absorption.py
mp_api/client/routes/materials/alloys.py
mp_api/client/routes/materials/bonds.py
mp_api/client/routes/materials/chemenv.py
mp_api/client/routes/materials/dielectric.py
mp_api/client/routes/materials/doi.py
mp_api/client/routes/materials/elasticity.py
mp_api/client/routes/materials/electrodes.py
mp_api/client/routes/materials/electronic_structure.py
mp_api/client/routes/materials/eos.py
mp_api/client/routes/materials/grain_boundaries.py
mp_api/client/routes/materials/magnetism.py
mp_api/client/routes/materials/materials.py
mp_api/client/routes/materials/oxidation_states.py
mp_api/client/routes/materials/phonon.py
mp_api/client/routes/materials/piezo.py
mp_api/client/routes/materials/provenance.py
mp_api/client/routes/materials/robocrys.py
mp_api/client/routes/materials/similarity.py
mp_api/client/routes/materials/substrates.py
mp_api/client/routes/materials/summary.py
mp_api/client/routes/materials/surface_properties.py
mp_api/client/routes/materials/synthesis.py
mp_api/client/routes/materials/tasks.py
mp_api/client/routes/materials/thermo.py
mp_api/client/routes/materials/xas.py
mp_api/client/routes/molecules/__init__.py
mp_api/client/routes/molecules/bonds.py
mp_api/client/routes/molecules/jcesr.py
mp_api/client/routes/molecules/molecules.py
mp_api/client/routes/molecules/orbitals.py
mp_api/client/routes/molecules/partial_charges.py
mp_api/client/routes/molecules/partial_spins.py
mp_api/client/routes/molecules/redox.py
mp_api/client/routes/molecules/summary.py
mp_api/client/routes/molecules/tasks.py
mp_api-0.45.15.dist-info/licenses/LICENSE
mp_api-0.45.15.dist-info/METADATA
mp_api-0.45.15.dist-info/WHEEL
mp_api-0.45.15.dist-info/top_level.txt
mp_api-0.45.15.dist-info/RECORD
