Metadata-Version: 2.4
Name: mp-api
Version: 0.45.15
Summary: API Client for the Materials Project
Author-email: The Materials Project <feedback@materialsproject.org>
License: modified BSD
Classifier: Programming Language :: Python :: 3
Classifier: Development Status :: 4 - Beta
Classifier: Intended Audience :: Science/Research
Classifier: Intended Audience :: Information Technology
Classifier: Operating System :: OS Independent
Classifier: Topic :: Scientific/Engineering
Requires-Python: >=3.10
License-File: LICENSE
Requires-Dist: msgpack
Requires-Dist: pymatgen!=2024.2.20,>=2022.3.7
Requires-Dist: typing-extensions>=3.7.4.1
Requires-Dist: requests>=2.23.0
Requires-Dist: monty>=2024.12.10
Requires-Dist: emmet-core>=0.86.2
Requires-Dist: smart_open
Requires-Dist: boto3
Requires-Dist: orjson<4,>=3.10
Provides-Extra: all
Requires-Dist: emmet-core[all]>=0.86.2; extra == "all"
Requires-Dist: custodian; extra == "all"
Requires-Dist: mpcontribs-client>=5.10; extra == "all"
Provides-Extra: test
Requires-Dist: pre-commit; extra == "test"
Requires-Dist: pytest; extra == "test"
Requires-Dist: pytest-asyncio; extra == "test"
Requires-Dist: pytest-cov; extra == "test"
Requires-Dist: pytest-mock; extra == "test"
Requires-Dist: pytest-xdist; extra == "test"
Requires-Dist: flake8; extra == "test"
Requires-Dist: pycodestyle; extra == "test"
Requires-Dist: mypy; extra == "test"
Requires-Dist: mypy-extensions; extra == "test"
Requires-Dist: typing-extensions; extra == "test"
Requires-Dist: types-setuptools; extra == "test"
Requires-Dist: types-requests; extra == "test"
Provides-Extra: docs
Requires-Dist: sphinx; extra == "docs"
Dynamic: license-file
